docx2python/__init__.py
docx2python/attribute_register.py
docx2python/bullets_and_numbering.py
docx2python/depth_collector.py
docx2python/docx_context.py
docx2python/docx_output.py
docx2python/docx_reader.py
docx2python/docx_text.py
docx2python/forms.py
docx2python/iterators.py
docx2python/main.py
docx2python/merge_runs.py
docx2python/namespace.py
docx2python/numbering_formats.py
docx2python/py.typed
docx2python/text_runs.py
docx2python/utilities.py
docx2python-3.6.1.dist-info/licenses/LICENSE.txt
docx2python-3.6.1.dist-info/METADATA
docx2python-3.6.1.dist-info/WHEEL
docx2python-3.6.1.dist-info/top_level.txt
docx2python-3.6.1.dist-info/RECORD
