Metadata-Version: 2.4
Name: docx2python
Version: 3.6.1
Summary: Extract content from docx files
Author-email: Shay Hill <shay_public@hotmail.com>
License: MIT
Requires-Python: >=3.10.0
License-File: LICENSE.txt
Requires-Dist: lxml
Requires-Dist: paragraphs
Requires-Dist: typing_extensions
Requires-Dist: types-lxml
Provides-Extra: dev
Requires-Dist: commitizen; extra == "dev"
Requires-Dist: pre-commit; extra == "dev"
Requires-Dist: pytest; extra == "dev"
Requires-Dist: tox; extra == "dev"
Requires-Dist: types-lxml; extra == "dev"
Dynamic: license-file
